[{"additions":{},"id":"8aea18088162540d018171544aa20056","externalId":"05345829435002","name":"HENSON PTY (LTD)","description":"Business profile","isMaster":false,"status":"ENABLED","validFromDate":null,"validFromTime":null,"validUntilDate":null,"validUntilTime":null,"customerCategory":null},{"additions":{},"id":"8aea18088162540d0181716c0a9b0076","externalId":"05345829545002","name":"MCDOWELL PTY (LTD)","description":"Business profile","isMaster":false,"status":"ENABLED","validFromDate":null,"validFromTime":null,"validUntilDate":null,"validUntilTime":null,"customerCategory":null},{"additions":{},"id":"8aea19078613326f01861735cd1c0018","externalId":"05306324625002","name":"SIT NOE","description":"Business profile","isMaster":false,"status":"ENABLED","validFromDate":null,"validFromTime":null,"validUntilDate":null,"validUntilTime":null,"customerCategory":null},{"additions":{},"id":"8aea19147d245714017d2dfc04d600a7","externalId":"05336920745002","name":"CELESTIALS","description":"Business profile","isMaster":false,"status":"ENABLED","validFromDate":null,"validFromTime":null,"validUntilDate":null,"validUntilTime":null,"customerCategory":null},{"additions":{},"id":"8aea19147d245714017d2dfc310d00f4","externalId":"05317121205002","name":"CORP X","description":"Business profile","isMaster":false,"status":"ENABLED","validFromDate":null,"validFromTime":null,"validUntilDate":null,"validUntilTime":null,"customerCategory":null},{"additions":{},"id":"8aea19147d245714017d2dfc6a7601cf","externalId":"05316557775002","name":"ATHITHI OBB DATA","description":"Business profile","isMaster":false,"status":"ENABLED","validFromDate":null,"validFromTime":null,"validUntilDate":null,"validUntilTime":null,"customerCategory":null},{"additions":{},"id":"8aea19147d245714017d2e33072503bd","externalId":"05331914305002","name":"SHIV EXPRTS","description":"Business profile","isMaster":false,"status":"ENABLED","validFromDate":null,"validFromTime":null,"validUntilDate":null,"validUntilTime":null,"customerCategory":null}]